pytoqlik/__init__.py
pytoqlik/module.py
pytoqlik/pytoqlik.py
pytoqlik-0.0.10.dist-info/LICENSE
pytoqlik-0.0.10.dist-info/METADATA
pytoqlik-0.0.10.dist-info/WHEEL
pytoqlik-0.0.10.dist-info/top_level.txt
pytoqlik-0.0.10.dist-info/RECORD
