Metadata-Version: 2.1
Name: pytoqlik
Version: 0.0.10
Summary: This lib allows you to integrate qlik with jupyter notebook.
Home-page: https://github.com/bixtecnologia/pytoqlik
Author: Angelo Baruffi Nogueira
Author-email: angelo.baruffi@bixtecnologia.com.br
License: UNKNOWN
Project-URL: Bug Tracker, https://github.com/bixtecnologia/pytoqlik/issues
Platform: UNKNOWN
Classifier: Programming Language :: Python :: 3
Classifier: License :: OSI Approved :: MIT License
Classifier: Operating System :: OS Independent
Requires-Python: >=3.6
License-File: LICENSE
Requires-Dist: pandas
Requires-Dist: websocket-client
